{
  "_meta": {
    "description": "Substack publications polled via public RSS ({URL}/feed). Raw feed: title + excerpt + link + entity tags, no AI. Free posts give full-ish content in RSS; paid posts give preview only. We store only a short excerpt (capped at 280 chars) either way and always link back to the original post.",
    "last_updated": "2026-06-09",
    "validation_status": "20 publications curated by Jorge. Marc Stein verified earlier; the other 19 are pending local validation. Custom-domain Substacks (truehoop.com, houseofstrauss.com, etc.) need a matching entry in the CORS Worker allowlist for the BROWSER live-fetch to reach them — handled in the same PR (worker-cors/src/index.js). The server-side poll_substack.py poller is uncostrained by CORS, so it picks these up immediately. Validate locally with: `python -m scripts.poll_substack --dry-run --since-hours 168 -v` and prune any feed that 404s."
  },
  "publications": [
    {
      "slug": "marcstein",
      "name": "The Stein Line",
      "feed": "https://marcstein.substack.com/feed",
      "validation": "verified 2026-05-24 — live, NBA content, entity tagging working"
    },
    {
      "slug": "truehoop",
      "name": "TrueHoop",
      "feed": "https://www.truehoop.com/feed",
      "validation": "unverified — custom-domain Substack, needs Worker allowlist + local dry-run check"
    },
    {
      "slug": "tomthefinder",
      "name": "The Finder",
      "feed": "https://www.tomthefinder.com/feed",
      "validation": "unverified"
    },
    {
      "slug": "houseofstrauss",
      "name": "House of Strauss",
      "feed": "https://www.houseofstrauss.com/feed",
      "validation": "unverified"
    },
    {
      "slug": "roycewebb",
      "name": "5x5",
      "feed": "https://www.roycewebb.com/feed",
      "validation": "unverified"
    },
    {
      "slug": "teamziller",
      "name": "Good Morning It's Basketball",
      "feed": "https://www.teamziller.com/feed",
      "validation": "unverified"
    },
    {
      "slug": "lastnightinbasketball",
      "name": "Last Night In Basketball",
      "feed": "https://www.lastnightinbasketball.com/feed",
      "validation": "unverified"
    },
    {
      "slug": "basketballintelligence",
      "name": "Basketball Intelligence",
      "feed": "https://www.basketballintelligence.net/feed",
      "validation": "unverified"
    },
    {
      "slug": "thirdapron",
      "name": "Third Apron",
      "feed": "https://www.thirdapron.com/feed",
      "validation": "unverified"
    },
    {
      "slug": "statitudes",
      "name": "Statitudes",
      "feed": "https://www.statitudes.com/feed",
      "validation": "unverified"
    },
    {
      "slug": "basketballfeelings",
      "name": "Basketball Feelings",
      "feed": "https://basketballfeelings.substack.com/feed",
      "validation": "unverified"
    },
    {
      "slug": "noceilingsnba",
      "name": "No Ceilings",
      "feed": "https://www.noceilingsnba.com/feed",
      "validation": "unverified"
    },
    {
      "slug": "nbabigboard",
      "name": "NBA Big Board",
      "feed": "https://www.nbabigboard.com/feed",
      "validation": "unverified"
    },
    {
      "slug": "edemirnba",
      "name": "Ersin's NBA Draft Newsletter",
      "feed": "https://edemirnba.substack.com/feed",
      "validation": "unverified"
    },
    {
      "slug": "draftstack",
      "name": "Draftstack",
      "feed": "https://draftstack.substack.com/feed",
      "validation": "unverified"
    },
    {
      "slug": "subtsakalidis",
      "name": "SubTsakalidis",
      "feed": "https://subtsakalidis.substack.com/feed",
      "validation": "unverified"
    },
    {
      "slug": "fieldhousefiles",
      "name": "Fieldhouse Files",
      "feed": "https://www.fieldhousefiles.com/feed",
      "validation": "unverified"
    },
    {
      "slug": "dubshub",
      "name": "The Dubs Hub",
      "feed": "https://dubshub.substack.com/feed",
      "validation": "unverified"
    },
    {
      "slug": "byderekjames",
      "name": "By Derek James",
      "feed": "https://byderekjames.substack.com/feed",
      "validation": "unverified"
    },
    {
      "slug": "zachdraft",
      "name": "Zach's Draft Substack",
      "feed": "https://zachdraft.substack.com/feed",
      "validation": "unverified"
    },
    {
      "slug": "chartinghoops",
      "name": "Charting Hoops",
      "feed": "https://chartinghoops.substack.com/feed",
      "validation": "unverified — added 2026-06-09 (Chris Gunther), pending local dry-run"
    },
    {
      "slug": "neilpaine",
      "name": "Neil's Substack",
      "feed": "https://neilpaine.substack.com/feed",
      "validation": "unverified — added 2026-06-09 (Neil Paine). NOTE: multi-sport, not NBA-only; canonical entity tagging filters NBA relevance downstream. Prune if too noisy."
    },
    {
      "slug": "digginbasketball",
      "name": "Diggin' Basketball",
      "feed": "https://digginbasketball.substack.com/feed",
      "validation": "unverified — added 2026-06-09, pending local dry-run"
    },
    {
      "slug": "basketballpoetry",
      "name": "Basketball Poetry",
      "feed": "https://www.basketballpoetry.com/feed",
      "validation": "unverified — added 2026-06-09, custom-domain Substack (needs Worker allowlist for browser live-fetch); pending local dry-run. If www 404s, try apex https://basketballpoetry.com/feed."
    }
  ]
}
