{
  "generated_at": "2026-05-27T01:30:37Z",
  "window_hours": 72,
  "weights": {
    "youtube": 1.3,
    "substack": 1.3,
    "google-news": 1.1,
    "bluesky": 1.0,
    "reddit": 1.0
  },
  "count": 40,
  "items": [
    {
      "id": "bs-did%3Aplc%3Apaf4vetn26bu7uggsie3vyrc%2Fapp.bsky.feed.post%2F3mmse6fnldc2u",
      "source": "bluesky",
      "published_at": "2026-05-27T01:28:51Z",
      "title": "Yeah, there's a first bump, and then there's what Keldon Johnson just did to Chet Holmgren",
      "url": "https://bsky.app/profile/lawmurraythenu.bsky.social/post/3mmse6fnldc2u",
      "author": "Law Murray 📘",
      "thumbnail": null,
      "body_excerpt": "Yeah, there's a first bump, and then there's what Keldon Johnson just did to Chet Holmgren\n\nChet gonna have a tomato on his chest after that one.",
      "players": [
        "chet-holmgren"
      ],
      "teams": [],
      "trending_score": 0.3458
    },
    {
      "id": "bs-did%3Aplc%3Aj24jtz7xkt5ttdsk32mmpkvn%2Fapp.bsky.feed.post%2F3mmse5xb3y22w",
      "source": "bluesky",
      "published_at": "2026-05-27T01:28:36Z",
      "title": "Just drafted Keldon Johnson in my fantasy football league",
      "url": "https://bsky.app/profile/johnhollinger.bsky.social/post/3mmse5xb3y22w",
      "author": "John Hollinger",
      "thumbnail": null,
      "body_excerpt": "Just drafted Keldon Johnson in my fantasy football league",
      "players": [],
      "teams": [],
      "trending_score": 0.3448
    },
    {
      "id": "bs-did%3Aplc%3Apaf4vetn26bu7uggsie3vyrc%2Fapp.bsky.feed.post%2F3mmse3nza322u",
      "source": "bluesky",
      "published_at": "2026-05-27T01:27:19Z",
      "title": "Stephon Castle might as well be the two on Shai Gilgeous-Alexander's chest",
      "url": "https://bsky.app/profile/lawmurraythenu.bsky.social/post/3mmse3nza322u",
      "author": "Law Murray 📘",
      "thumbnail": null,
      "body_excerpt": "Stephon Castle might as well be the two on Shai Gilgeous-Alexander's chest",
      "players": [
        "shai-gilgeous-alexander"
      ],
      "teams": [],
      "trending_score": 0.3394
    },
    {
      "id": "bs-did%3Aplc%3A4xpj3xjxsxxcuh3ghaulzdqu%2Fapp.bsky.feed.post%2F3mmse3mgtrc2r",
      "source": "bluesky",
      "published_at": "2026-05-27T01:27:17Z",
      "title": "It feels like Castle was built in a lab to guard SGA.",
      "url": "https://bsky.app/profile/yourmandevine.bsky.social/post/3mmse3mgtrc2r",
      "author": "Dan Devine",
      "thumbnail": null,
      "body_excerpt": "It feels like Castle was built in a lab to guard SGA.",
      "players": [
        "shai-gilgeous-alexander"
      ],
      "teams": [
        "washington-wizards"
      ],
      "trending_score": 0.3393
    },
    {
      "id": "bs-did%3Aplc%3A5dwbpojkp6wykwcafasvwroi%2Fapp.bsky.feed.post%2F3mmse2k7wns2b",
      "source": "bluesky",
      "published_at": "2026-05-27T01:26:41Z",
      "title": "The Warriors tomorrow are bringing in Miami guard Tre Donaldson, Texas Tech forward Dillon Mitchell and Vanderbilt forward Tyler Nickel for a pre-draft workout @nbcswarriors.bsky.social",
      "url": "https://bsky.app/profile/daltonjohnson.bsky.social/post/3mmse2k7wns2b",
      "author": "Dalton Johnson",
      "thumbnail": null,
      "body_excerpt": "The Warriors tomorrow are bringing in Miami guard Tre Donaldson, Texas Tech forward Dillon Mitchell and Vanderbilt forward Tyler Nickel for a pre-draft workout @nbcswarriors.bsky.social",
      "players": [
        "donovan-mitchell"
      ],
      "teams": [
        "golden-state-warriors"
      ],
      "trending_score": 0.3368
    },
    {
      "id": "bs-did%3Aplc%3Alymzh2dxwzgjibwhgvwxhwla%2Fapp.bsky.feed.post%2F3mmsdzqqivs23",
      "source": "bluesky",
      "published_at": "2026-05-27T01:26:15Z",
      "title": "Mark Stone has more goals in four periods this series than any Avs player (besides Gabe) has in all four games.",
      "url": "https://bsky.app/profile/shapalicious.bsky.social/post/3mmsdzqqivs23",
      "author": "Jake Shapiro",
      "thumbnail": null,
      "body_excerpt": "Mark Stone has more goals in four periods this series than any Avs player (besides Gabe) has in all four games.",
      "players": [],
      "teams": [],
      "trending_score": 0.3351
    },
    {
      "id": "bs-did%3Aplc%3Ablrk2gk5dq32snk2kthu3cnn%2Fapp.bsky.feed.post%2F3mmsdxdm4ms2y",
      "source": "bluesky",
      "published_at": "2026-05-27T01:24:54Z",
      "title": "Thunder win the first stretch of non-SGA minutes by 4.",
      "url": "https://bsky.app/profile/keerthikau.bsky.social/post/3mmsdxdm4ms2y",
      "author": "Keerthika Uthayakumar",
      "thumbnail": null,
      "body_excerpt": "Thunder win the first stretch of non-SGA minutes by 4.",
      "players": [
        "shai-gilgeous-alexander"
      ],
      "teams": [
        "oklahoma-city-thunder"
      ],
      "trending_score": 0.3297
    },
    {
      "id": "bs-did%3Aplc%3Apaf4vetn26bu7uggsie3vyrc%2Fapp.bsky.feed.post%2F3mmsdx5byu22o",
      "source": "bluesky",
      "published_at": "2026-05-27T01:24:47Z",
      "title": "Chet Holmgren has tried to use the baseline as a help defender multiple times but drivers are just getting into and/or through his body and finding layups.",
      "url": "https://bsky.app/profile/lawmurraythenu.bsky.social/post/3mmsdx5byu22o",
      "author": "Law Murray 📘",
      "thumbnail": null,
      "body_excerpt": "Chet Holmgren has tried to use the baseline as a help defender multiple times but drivers are just getting into and/or through his body and finding layups.",
      "players": [
        "chet-holmgren"
      ],
      "teams": [],
      "trending_score": 0.3292
    },
    {
      "id": "bs-did%3Aplc%3Alymzh2dxwzgjibwhgvwxhwla%2Fapp.bsky.feed.post%2F3mmsdwruaqs23",
      "source": "bluesky",
      "published_at": "2026-05-27T01:24:35Z",
      "title": "brutal play from Kadri and Toews there",
      "url": "https://bsky.app/profile/shapalicious.bsky.social/post/3mmsdwruaqs23",
      "author": "Jake Shapiro",
      "thumbnail": null,
      "body_excerpt": "brutal play from Kadri and Toews there",
      "players": [],
      "teams": [],
      "trending_score": 0.3284
    },
    {
      "id": "bs-did%3Aplc%3Azgw663lwxmujmen5k4jmjair%2Fapp.bsky.feed.post%2F3mmsdvkyqr22e",
      "source": "bluesky",
      "published_at": "2026-05-27T01:23:54Z",
      "title": "reggie miller says he thinks the knicks will be favored to win the finals no matter who wins the spurs-thunder series. he's wrong, but what a time to be alive.",
      "url": "https://bsky.app/profile/danfavale.bsky.social/post/3mmsdvkyqr22e",
      "author": "dan favale",
      "thumbnail": null,
      "body_excerpt": "reggie miller says he thinks the knicks will be favored to win the finals no matter who wins the spurs-thunder series. he's wrong, but what a time to be alive.",
      "players": [],
      "teams": [
        "new-orleans-pelicans",
        "new-york-knicks",
        "oklahoma-city-thunder",
        "san-antonio-spurs"
      ],
      "trending_score": 0.3258
    },
    {
      "id": "gn-0948d010262348a5",
      "source": "google-news",
      "published_at": "2026-05-27T01:14:00Z",
      "title": "NBA: Playoffs-San Antonio Spurs at Oklahoma City Thunder",
      "url": "https://news.google.com/rss/articles/CBMi6wFBVV95cUxNamJSUEZKb1ZVMmp6bkM2cE5nSXRvdmxTcndHRTQwR1ZnV0lUTWhGOFN2ZXUxQU9Qb1p6c09vdkp3ZGhZQ3dUX2dnYzlzYnBzYlVQc0cwUG85ajczemx6VGlhUUs1ZTVqUUVHNk5aUDFRVFpWQkVHaXRCd2JlRGc5eXotX0xhd3prMFlEVU81SmR5QjdKaGhkNVRFYjkxTnhGM3FKTHAxZjgybTBKVUs2bWVCemE1U3kxZWVrdmhNRGo5ZzVaM1hIVU5jYmpKVVQzcVdxdl9scjNjcURXNzBVejFaOEh3dmZYY3NV?oc=5",
      "author": "Reuters Connect",
      "thumbnail": null,
      "body_excerpt": "NBA: Playoffs-San Antonio Spurs at Oklahoma City Thunder Reuters Connect",
      "players": [],
      "teams": [
        "oklahoma-city-thunder",
        "san-antonio-spurs"
      ],
      "trending_score": 0.3201
    },
    {
      "id": "bs-did%3Aplc%3Amx62ni2prhriaagd7jfa65zk%2Fapp.bsky.feed.post%2F3mmsdrludck2n",
      "source": "bluesky",
      "published_at": "2026-05-27T01:21:41Z",
      "title": "You have to look at how quick OKC is making a decision to kick as soon as they see Wembanyama pull in to the paint. Spurs have always worked to rotate around him but it's going to be key in this one.",
      "url": "https://bsky.app/profile/stevejones20.bsky.social/post/3mmsdrludck2n",
      "author": "Steve Jones",
      "thumbnail": null,
      "body_excerpt": "You have to look at how quick OKC is making a decision to kick as soon as they see Wembanyama pull in to the paint. Spurs have always worked to rotate around him but it's going to be key in this one.",
      "players": [
        "victor-wembanyama"
      ],
      "teams": [
        "oklahoma-city-thunder",
        "san-antonio-spurs"
      ],
      "trending_score": 0.3174
    },
    {
      "id": "bs-did%3Aplc%3Atna6odclgfacu2mwyoc4tfvo%2Fapp.bsky.feed.post%2F3mmsdrhkoz22v",
      "source": "bluesky",
      "published_at": "2026-05-27T01:21:37Z",
      "title": " www.nytimes.com/athletic/vid...",
      "url": "https://bsky.app/profile/byjayking.bsky.social/post/3mmsdrhkoz22v",
      "author": "Jay King",
      "thumbnail": null,
      "body_excerpt": " www.nytimes.com/athletic/vid...",
      "players": [],
      "teams": [],
      "trending_score": 0.3172
    },
    {
      "id": "bs-did%3Aplc%3Amx62ni2prhriaagd7jfa65zk%2Fapp.bsky.feed.post%2F3mmsdlpbvqk2n",
      "source": "bluesky",
      "published_at": "2026-05-27T01:18:23Z",
      "title": "I said the Spurs need to find a way to sustain their defense when Shai plays well. They certainly can't afford to get dinged when he's quieter than usual.",
      "url": "https://bsky.app/profile/stevejones20.bsky.social/post/3mmsdlpbvqk2n",
      "author": "Steve Jones",
      "thumbnail": null,
      "body_excerpt": "I said the Spurs need to find a way to sustain their defense when Shai plays well. They certainly can't afford to get dinged when he's quieter than usual.",
      "players": [
        "shai-gilgeous-alexander"
      ],
      "teams": [
        "san-antonio-spurs"
      ],
      "trending_score": 0.3056
    },
    {
      "id": "bs-did%3Aplc%3Ahb5s4bd5ctk6inznrn6gf6hx%2Fapp.bsky.feed.post%2F3mmsdjp2juf2x",
      "source": "bluesky",
      "published_at": "2026-05-27T01:17:16Z",
      "title": "Dear Thunder fans, you don't get to boo that Wemby move to draw a foul when your team employs SGA. Thank you for your attention to this matter.",
      "url": "https://bsky.app/profile/basketballtalk.bsky.social/post/3mmsdjp2juf2x",
      "author": "Kurt Helin",
      "thumbnail": null,
      "body_excerpt": "Dear Thunder fans, you don't get to boo that Wemby move to draw a foul when your team employs SGA. Thank you for your attention to this matter.",
      "players": [
        "shai-gilgeous-alexander",
        "victor-wembanyama"
      ],
      "teams": [
        "oklahoma-city-thunder"
      ],
      "trending_score": 0.3018
    },
    {
      "id": "bs-did%3Aplc%3Amx62ni2prhriaagd7jfa65zk%2Fapp.bsky.feed.post%2F3mmsdjkt2d22n",
      "source": "bluesky",
      "published_at": "2026-05-27T01:17:12Z",
      "title": "OKC looking to drive but looking to use those drives to poke at the Spurs rotations and Wemby. Wallace drives vs. Barnes, Wembanyama pulls into the paint to help. Skip pass is there to Caruso, rotation is there. Extra to Williams for 3.",
      "url": "https://bsky.app/profile/stevejones20.bsky.social/post/3mmsdjkt2d22n",
      "author": "Steve Jones",
      "thumbnail": null,
      "body_excerpt": "OKC looking to drive but looking to use those drives to poke at the Spurs rotations and Wemby. Wallace drives vs. Barnes, Wembanyama pulls into the paint to help. Skip pass is there to Caruso, rotation is there. Extra to Williams for 3.",
      "players": [
        "jalen-williams",
        "scottie-barnes",
        "victor-wembanyama"
      ],
      "teams": [
        "oklahoma-city-thunder",
        "san-antonio-spurs"
      ],
      "trending_score": 0.3016
    },
    {
      "id": "bs-did%3Aplc%3A6ahv2jk7wea2fql74oiisng6%2Fapp.bsky.feed.post%2F3mmsdhqhtds2k",
      "source": "bluesky",
      "published_at": "2026-05-27T01:16:10Z",
      "title": "Caitlin Clark finally got her first Indy 500 experience — serving as Grand Marshal in front of more than 330,000 fans.",
      "url": "https://bsky.app/profile/scottagness.bsky.social/post/3mmsdhqhtds2k",
      "author": "Scott Agness",
      "thumbnail": null,
      "body_excerpt": "Caitlin Clark finally got her first Indy 500 experience — serving as Grand Marshal in front of more than 330,000 fans.\n\nShe wasn’t alone: Hull, White and more than half the Pacers roster witnessed the closest finish in race history.\n\nStory + video: www.fieldhousefiles.com/p/caitlin-cl...",
      "players": [],
      "teams": [
        "indiana-pacers"
      ],
      "trending_score": 0.2981
    },
    {
      "id": "bs-did%3Aplc%3Ahb5s4bd5ctk6inznrn6gf6hx%2Fapp.bsky.feed.post%2F3mmsdfnvw6d24",
      "source": "bluesky",
      "published_at": "2026-05-27T01:15:00Z",
      "title": "After a rough shooting Game 4, the Thunder bench is 5-of-8 to start Game 5.",
      "url": "https://bsky.app/profile/basketballtalk.bsky.social/post/3mmsdfnvw6d24",
      "author": "Kurt Helin",
      "thumbnail": null,
      "body_excerpt": "After a rough shooting Game 4, the Thunder bench is 5-of-8 to start Game 5.",
      "players": [],
      "teams": [
        "oklahoma-city-thunder"
      ],
      "trending_score": 0.2942
    },
    {
      "id": "bs-did%3Aplc%3Amx62ni2prhriaagd7jfa65zk%2Fapp.bsky.feed.post%2F3mmsdfgjfr22n",
      "source": "bluesky",
      "published_at": "2026-05-27T01:14:53Z",
      "title": "OKC poking at the Spurs defense and playing out of breakdowns and Wemby's rotations. Chet screens and the Spurs switch that. Chet works to seal. Advance to McCain who gets a screen from Williams. No switch, roll is there and Wemby helps from strong side corner. Open 3 there.",
      "url": "https://bsky.app/profile/stevejones20.bsky.social/post/3mmsdfgjfr22n",
      "author": "Steve Jones",
      "thumbnail": null,
      "body_excerpt": "OKC poking at the Spurs defense and playing out of breakdowns and Wemby's rotations. Chet screens and the Spurs switch that. Chet works to seal. Advance to McCain who gets a screen from Williams. No switch, roll is there and Wemby helps from strong side corner. Open 3 there.",
      "players": [
        "chet-holmgren",
        "jalen-williams",
        "victor-wembanyama"
      ],
      "teams": [
        "new-orleans-pelicans",
        "oklahoma-city-thunder",
        "san-antonio-spurs"
      ],
      "trending_score": 0.2939
    },
    {
      "id": "bs-did%3Aplc%3Apaf4vetn26bu7uggsie3vyrc%2Fapp.bsky.feed.post%2F3mmsdd3cm6k2o",
      "source": "bluesky",
      "published_at": "2026-05-27T01:13:34Z",
      "title": "All four Thunderbuddy reserves have made a 3",
      "url": "https://bsky.app/profile/lawmurraythenu.bsky.social/post/3mmsdd3cm6k2o",
      "author": "Law Murray 📘",
      "thumbnail": null,
      "body_excerpt": "All four Thunderbuddy reserves have made a 3\n\nThe Thunder bench (including McCain) made only five 3s in all of Game 4, with two of them coming in a non-competitive fourth quarter.",
      "players": [],
      "teams": [
        "oklahoma-city-thunder"
      ],
      "trending_score": 0.2896
    },
    {
      "id": "bs-did%3Aplc%3Agqgnr2obuwossobfnxw5xnxg%2Fapp.bsky.feed.post%2F3mmsd6wght227",
      "source": "bluesky",
      "published_at": "2026-05-27T01:11:15Z",
      "title": "Hollinger POTD Mehmet Okur. Turkish big was drafted 37th by DET in 01. Came to NBA in 02 & was good bench guy but annoyed Larry Brown. Signed big deal w/UTA in 04, scored 18 ppg & was all-star. Great stretch big but weak on D. In all, a very good player.",
      "url": "https://bsky.app/profile/hoopsanalyst.bsky.social/post/3mmsd6wght227",
      "author": "HoopsAnalyst",
      "thumbnail": null,
      "body_excerpt": "Hollinger POTD Mehmet Okur. Turkish big was drafted 37th by DET in 01. Came to NBA in 02 & was good bench guy but annoyed Larry Brown. Signed big deal w/UTA in 04, scored 18 ppg & was all-star. Great stretch big but weak on D. In all, a very good player.",
      "players": [
        "jaylen-brown"
      ],
      "teams": [
        "detroit-pistons",
        "utah-jazz",
        "washington-wizards"
      ],
      "trending_score": 0.2825
    },
    {
      "id": "bs-did%3Aplc%3Awmqeyoxhxyod73wcot4sqhe7%2Fapp.bsky.feed.post%2F3mmsd634trc2n",
      "source": "bluesky",
      "published_at": "2026-05-27T01:10:46Z",
      "title": "every possession in this game feels like 4th and inches in the 4th quarter of a one-score football game",
      "url": "https://bsky.app/profile/jonhamm.bsky.social/post/3mmsd634trc2n",
      "author": "Jon Hamm",
      "thumbnail": null,
      "body_excerpt": "every possession in this game feels like 4th and inches in the 4th quarter of a one-score football game",
      "players": [],
      "teams": [],
      "trending_score": 0.281
    },
    {
      "id": "bs-did%3Aplc%3As42iw2fbfmgsgh7hdtvvoaao%2Fapp.bsky.feed.post%2F3mmsd3lb3lk2q",
      "source": "bluesky",
      "published_at": "2026-05-27T01:09:22Z",
      "title": "(no text)",
      "url": "https://bsky.app/profile/hoopinformatics.bsky.social/post/3mmsd3lb3lk2q",
      "author": "Hoop Informatics",
      "thumbnail": null,
      "body_excerpt": "",
      "players": [],
      "teams": [],
      "trending_score": 0.2768
    },
    {
      "id": "bs-did%3Aplc%3Azgw663lwxmujmen5k4jmjair%2Fapp.bsky.feed.post%2F3mmsd2aq6r22r",
      "source": "bluesky",
      "published_at": "2026-05-27T01:08:38Z",
      "title": "the executive responsible for these drone cams at the start of each game/quarter",
      "url": "https://bsky.app/profile/danfavale.bsky.social/post/3mmsd2aq6r22r",
      "author": "dan favale",
      "thumbnail": null,
      "body_excerpt": "the executive responsible for these drone cams at the start of each game/quarter",
      "players": [],
      "teams": [],
      "trending_score": 0.2747
    },
    {
      "id": "bs-did%3Aplc%3Ao7nvaeky6b42dplp2ssdudvw%2Fapp.bsky.feed.post%2F3mmscxutb6c2z",
      "source": "bluesky",
      "published_at": "2026-05-27T01:07:18Z",
      "title": "🤣🤣🤣",
      "url": "https://bsky.app/profile/ohnohedidnt24.bsky.social/post/3mmscxutb6c2z",
      "author": "Oh No He Didn't",
      "thumbnail": null,
      "body_excerpt": "🤣🤣🤣",
      "players": [],
      "teams": [],
      "trending_score": 0.2709
    },
    {
      "id": "bs-did%3Aplc%3Apaf4vetn26bu7uggsie3vyrc%2Fapp.bsky.feed.post%2F3mmscxa6atc2o",
      "source": "bluesky",
      "published_at": "2026-05-27T01:06:56Z",
      "title": "Spurs outscored Thunder 11-6 off turnovers in that first quarter. Thunder allowed the 2nd-fewest points off turnovers allowed in regular season (14.7, only Boston allowed fewer)",
      "url": "https://bsky.app/profile/lawmurraythenu.bsky.social/post/3mmscxa6atc2o",
      "author": "Law Murray 📘",
      "thumbnail": null,
      "body_excerpt": "Spurs outscored Thunder 11-6 off turnovers in that first quarter. Thunder allowed the 2nd-fewest points off turnovers allowed in regular season (14.7, only Boston allowed fewer)\n\nOklahoma City did even that out by outscoring Spurs 7-2 on 2nd-chance points.",
      "players": [],
      "teams": [
        "oklahoma-city-thunder",
        "san-antonio-spurs"
      ],
      "trending_score": 0.2698
    },
    {
      "id": "bs-did%3Aplc%3A7sfnardo5xxznxc6esxc5ooe%2Fapp.bsky.feed.post%2F3mmscwt2ce22r",
      "source": "bluesky",
      "published_at": "2026-05-27T01:06:43Z",
      "title": "OKC leads SAS 29-27 after 1Q.",
      "url": "https://bsky.app/profile/nba.com/post/3mmscwt2ce22r",
      "author": "NBA",
      "thumbnail": null,
      "body_excerpt": "OKC leads SAS 29-27 after 1Q.\n\nChet Holmgren: 8 PTS, 4 REB\nJulian Champagnie: 13 PTS, 2 REB, 2 STL\n\n📺 2Q LIVE on NBC & Peacock: www.nba.com/how-to-watch...",
      "players": [
        "chet-holmgren"
      ],
      "teams": [
        "oklahoma-city-thunder",
        "san-antonio-spurs"
      ],
      "trending_score": 0.2692
    },
    {
      "id": "bs-did%3Aplc%3Apgok625ocobq7t3decm3o5vu%2Fapp.bsky.feed.post%2F3mmscus2rzl2p",
      "source": "bluesky",
      "published_at": "2026-05-27T01:05:34Z",
      "title": "OKC leading despite a 24% turnover rate, the 13-point quarter from Champagnie, and whatever was going on with SGA in the first seems bullish.",
      "url": "https://bsky.app/profile/jadubin5.bsky.social/post/3mmscus2rzl2p",
      "author": "Jared Dubin",
      "thumbnail": null,
      "body_excerpt": "OKC leading despite a 24% turnover rate, the 13-point quarter from Champagnie, and whatever was going on with SGA in the first seems bullish.",
      "players": [
        "shai-gilgeous-alexander"
      ],
      "teams": [
        "oklahoma-city-thunder",
        "washington-wizards"
      ],
      "trending_score": 0.266
    },
    {
      "id": "bs-did%3Aplc%3Alldgxx4auj7zsd2fp4hbory3%2Fapp.bsky.feed.post%2F3mmsctqyo2k2w",
      "source": "bluesky",
      "published_at": "2026-05-27T01:05:00Z",
      "title": "Spurs using the “Lebron” defense against SGA..",
      "url": "https://bsky.app/profile/markjonesespn.bsky.social/post/3mmsctqyo2k2w",
      "author": "Mark Jones",
      "thumbnail": null,
      "body_excerpt": "Spurs using the “Lebron” defense against SGA..\n\nHeavy gapping..\n\nGuarding him with all 5 players…like Spurs did vs Lebron in the 2007 Finals.",
      "players": [
        "lebron-james",
        "shai-gilgeous-alexander"
      ],
      "teams": [
        "san-antonio-spurs"
      ],
      "trending_score": 0.2645
    },
    {
      "id": "bs-did%3Aplc%3A75z3gabuwl6uvv7pootuuvgn%2Fapp.bsky.feed.post%2F3mmsctrtxul2n",
      "source": "bluesky",
      "published_at": "2026-05-27T01:05:00Z",
      "title": "Would you want to see the #Lakers sign Robert Williams III in free agency?",
      "url": "https://bsky.app/profile/lakersnation.bsky.social/post/3mmsctrtxul2n",
      "author": "LakersNation.com",
      "thumbnail": null,
      "body_excerpt": "Would you want to see the #Lakers sign Robert Williams III in free agency?\nlakersnation.com/lakers-rumor...",
      "players": [
        "jalen-williams"
      ],
      "teams": [
        "los-angeles-lakers"
      ],
      "trending_score": 0.2645
    },
    {
      "id": "bs-did%3Aplc%3Amx62ni2prhriaagd7jfa65zk%2Fapp.bsky.feed.post%2F3mmsct7vzuk2n",
      "source": "bluesky",
      "published_at": "2026-05-27T01:04:42Z",
      "title": "The Spurs getting that Carter Bryant surge only for OKC to do *that* in the last 30 seconds sure is something.",
      "url": "https://bsky.app/profile/stevejones20.bsky.social/post/3mmsct7vzuk2n",
      "author": "Steve Jones",
      "thumbnail": null,
      "body_excerpt": "The Spurs getting that Carter Bryant surge only for OKC to do *that* in the last 30 seconds sure is something.",
      "players": [],
      "teams": [
        "oklahoma-city-thunder",
        "san-antonio-spurs"
      ],
      "trending_score": 0.2637
    },
    {
      "id": "bs-did%3Aplc%3Ax5ws4443357brulpdp7zl2qt%2Fapp.bsky.feed.post%2F3mmscsib5622g",
      "source": "bluesky",
      "published_at": "2026-05-27T01:04:17Z",
      "title": "Dylan Harper is giving it a go but it’s pretty clear his adductor is not what it was three games ago.",
      "url": "https://bsky.app/profile/mikefinger.bsky.social/post/3mmscsib5622g",
      "author": "Mike Finger",
      "thumbnail": null,
      "body_excerpt": "Dylan Harper is giving it a go but it’s pretty clear his adductor is not what it was three games ago.",
      "players": [],
      "teams": [
        "washington-wizards"
      ],
      "trending_score": 0.2625
    },
    {
      "id": "bs-did%3Aplc%3Apaf4vetn26bu7uggsie3vyrc%2Fapp.bsky.feed.post%2F3mmscs4dtyk2o",
      "source": "bluesky",
      "published_at": "2026-05-27T01:04:05Z",
      "title": "Wemby load managed that first quarter",
      "url": "https://bsky.app/profile/lawmurraythenu.bsky.social/post/3mmscs4dtyk2o",
      "author": "Law Murray 📘",
      "thumbnail": null,
      "body_excerpt": "Wemby load managed that first quarter",
      "players": [
        "victor-wembanyama"
      ],
      "teams": [],
      "trending_score": 0.262
    },
    {
      "id": "bs-did%3Aplc%3Aj24jtz7xkt5ttdsk32mmpkvn%2Fapp.bsky.feed.post%2F3mmscrse6is2w",
      "source": "bluesky",
      "published_at": "2026-05-27T01:03:54Z",
      "title": "this series rules.",
      "url": "https://bsky.app/profile/johnhollinger.bsky.social/post/3mmscrse6is2w",
      "author": "John Hollinger",
      "thumbnail": null,
      "body_excerpt": "this series rules.",
      "players": [],
      "teams": [],
      "trending_score": 0.2615
    },
    {
      "id": "bs-did%3Aplc%3Amtyaifw46xppbvcxeo6tl6wf%2Fapp.bsky.feed.post%2F3mmscrehese2h",
      "source": "bluesky",
      "published_at": "2026-05-27T01:03:39Z",
      "title": "Julian Champagnie:",
      "url": "https://bsky.app/profile/nateduncannba.bsky.social/post/3mmscrehese2h",
      "author": "Nate Duncan",
      "thumbnail": null,
      "body_excerpt": "Julian Champagnie:\n\n\nRegular-season points per GAME: 11\n\n\nFirst-quarter points tonight: 13\n\n\nThe only other player with such a low scoring average to score so much in a conference finals or NBA Finals first quarter (play-by-play era) is Meyers Leonard in 2019.",
      "players": [
        "kawhi-leonard"
      ],
      "teams": [],
      "trending_score": 0.2608
    },
    {
      "id": "bs-did%3Aplc%3Apaf4vetn26bu7uggsie3vyrc%2Fapp.bsky.feed.post%2F3mmscqdvp4k2o",
      "source": "bluesky",
      "published_at": "2026-05-27T01:03:05Z",
      "title": "Just another reminder that Cason Wallace led the league in steals. You can't dribble haphazardly around him. Dylan Harper had to find out.",
      "url": "https://bsky.app/profile/lawmurraythenu.bsky.social/post/3mmscqdvp4k2o",
      "author": "Law Murray 📘",
      "thumbnail": null,
      "body_excerpt": "Just another reminder that Cason Wallace led the league in steals. You can't dribble haphazardly around him. Dylan Harper had to find out.",
      "players": [],
      "teams": [],
      "trending_score": 0.2593
    },
    {
      "id": "bs-did%3Aplc%3Awmqeyoxhxyod73wcot4sqhe7%2Fapp.bsky.feed.post%2F3mmscq67lxs2n",
      "source": "bluesky",
      "published_at": "2026-05-27T01:02:59Z",
      "title": "Caruso passed up a wide-open layup and passed it into air instead. Being selfish in life is fine now and then, guys.",
      "url": "https://bsky.app/profile/jonhamm.bsky.social/post/3mmscq67lxs2n",
      "author": "Jon Hamm",
      "thumbnail": null,
      "body_excerpt": "Caruso passed up a wide-open layup and passed it into air instead. Being selfish in life is fine now and then, guys.",
      "players": [],
      "teams": [],
      "trending_score": 0.2591
    },
    {
      "id": "bs-did%3Aplc%3A4xpj3xjxsxxcuh3ghaulzdqu%2Fapp.bsky.feed.post%2F3mmscplwhec2r",
      "source": "bluesky",
      "published_at": "2026-05-27T01:02:40Z",
      "title": "It's really incredible how good Cason Wallace is at just ripping the ball out of dudes' hands.",
      "url": "https://bsky.app/profile/yourmandevine.bsky.social/post/3mmscplwhec2r",
      "author": "Dan Devine",
      "thumbnail": null,
      "body_excerpt": "It's really incredible how good Cason Wallace is at just ripping the ball out of dudes' hands.",
      "players": [
        "lamelo-ball"
      ],
      "teams": [],
      "trending_score": 0.2582
    },
    {
      "id": "gn-d3f5ac41be21c7a6",
      "source": "google-news",
      "published_at": "2026-05-27T00:51:00Z",
      "title": "Jalen Williams out for Game 5",
      "url": "https://news.google.com/rss/articles/CBMipgFBVV95cUxPMUtDcmJ6eDRrOW94ZlBlZnNOQ3R0NHQtZFdNa0FkV3d4Y2J3eUF0M3B4VG11T1lFTXo1My1XdVhFRFhmazdEZjVNZi1RM1EyRU1ZMTcwMEszRnk5VEtGOUhXaHpNUWo5UmVmcGd3Y1FIeE5CLWlxQlA3TjN6a2V4a0dZX1BZMHNJUXdERmFzdTJBVW9KRWZJdW1hdzZxMlpMQldNVnpB?oc=5",
      "author": "HoopsHype",
      "thumbnail": null,
      "body_excerpt": "Jalen Williams out for Game 5 HoopsHype",
      "players": [
        "jalen-williams"
      ],
      "teams": [],
      "trending_score": 0.2535
    },
    {
      "id": "bs-did%3Aplc%3Ae7fdktkwv37ws6rljgnoljfz%2Fapp.bsky.feed.post%2F3mmscm4dsmk2b",
      "source": "bluesky",
      "published_at": "2026-05-27T01:00:43Z",
      "title": "New for @orlandosentinel.com: Joined by his brother, #Magic guard Anthony Black discussed Jamahl Mosley’s firing, the chance to sign an extension with Orlando and more.",
      "url": "https://bsky.app/profile/jbeede.bsky.social/post/3mmscm4dsmk2b",
      "author": "Jason Beede",
      "thumbnail": null,
      "body_excerpt": "New for @orlandosentinel.com: Joined by his brother, #Magic guard Anthony Black discussed Jamahl Mosley’s firing, the chance to sign an extension with Orlando and more.\n\n“It’s always tough to lose like that and see the results that come with it,” he said. www.orlandosentinel.com/2026/05/26/o...",
      "players": [],
      "teams": [
        "orlando-magic"
      ],
      "trending_score": 0.2532
    }
  ]
}
