{
  "generated_at": "2026-07-04T19:58:17Z",
  "window_hours": 72,
  "weights": {
    "youtube": 1.3,
    "substack": 1.3,
    "google-news": 1.1,
    "bluesky": 1.0,
    "reddit": 1.0
  },
  "count": 40,
  "items": [
    {
      "id": "bs-did%3Aplc%3Agqgnr2obuwossobfnxw5xnxg%2Fapp.bsky.feed.post%2F3mpttplmzvc2b",
      "source": "bluesky",
      "published_at": "2026-07-04T19:55:08Z",
      "title": "Bonus Hollander POTD Jawann Oldham. Seattle C was drafted 40th in 80 by DEN. Bounced around before getting time w/CHI in 83. NY traded for him in 86. After 1 unhappy yr in NY, bounced around more before retiring in 91. Good shotblocker. Also had epic fight w/Manute. RIP.",
      "url": "https://bsky.app/profile/hoopsanalyst.bsky.social/post/3mpttplmzvc2b",
      "author": "HoopsAnalyst",
      "thumbnail": "https://cdn.bsky.app/img/feed_fullsize/plain/did:plc:gqgnr2obuwossobfnxw5xnxg/bafkreifcwtz35rpydrbi3h4lzpqpbbs76g3dcm3ixg7enjkks7ky7upsua",
      "body_excerpt": "Bonus Hollander POTD Jawann Oldham. Seattle C was drafted 40th in 80 by DEN. Bounced around before getting time w/CHI in 83. NY traded for him in 86. After 1 unhappy yr in NY, bounced around more before retiring in 91. Good shotblocker. Also had epic fight w/Manute. RIP.",
      "players": [],
      "teams": [
        "chicago-bulls",
        "denver-nuggets"
      ],
      "media": {
        "type": "image",
        "images": [
          {
            "url": "https://cdn.bsky.app/img/feed_fullsize/plain/did:plc:gqgnr2obuwossobfnxw5xnxg/bafkreifcwtz35rpydrbi3h4lzpqpbbs76g3dcm3ixg7enjkks7ky7upsua",
            "alt": ""
          }
        ]
      },
      "trending_score": 0.3401
    },
    {
      "id": "gn-16bd61991ceceb2e",
      "source": "google-news",
      "published_at": "2026-07-04T19:46:38Z",
      "title": "His Dad Played Against Kobe. Now He’s a Laker.",
      "url": "https://news.google.com/rss/articles/CBMigwFBVV95cUxPT0hSWkF6Z1JhWVlLTTVwNGIyQ2tUbzJhdUg5TEFLRUlreGFiQXFqRzRROVk3bndtQTZEOXVXMUtTdC1DdmNtekM3bkhMV0JDU2ZjMUQyNjhJaDBFX0czc1RhZFBTYlpwLWZNWHZXMzlIQzJ4eEloeE15Z3FqQW5IdEd2NA?oc=5",
      "author": "NBA.com",
      "thumbnail": null,
      "body_excerpt": "His Dad Played Against Kobe. Now He’s a Laker. NBA.com",
      "players": [],
      "teams": [],
      "trending_score": 0.3384
    },
    {
      "id": "bs-did%3Aplc%3As42iw2fbfmgsgh7hdtvvoaao%2Fapp.bsky.feed.post%2F3mpttla2i7c26",
      "source": "bluesky",
      "published_at": "2026-07-04T19:52:42Z",
      "title": "A reminder as Summer League starts which stats can be meaningful (sticky-green) and which stats you should ignore (icky - red)",
      "url": "https://bsky.app/profile/hoopinformatics.bsky.social/post/3mpttla2i7c26",
      "author": "Hoop Informatics",
      "thumbnail": null,
      "body_excerpt": "A reminder as Summer League starts which stats can be meaningful (sticky-green) and which stats you should ignore (icky - red)",
      "players": [],
      "teams": [],
      "trending_score": 0.3302
    },
    {
      "id": "bs-did%3Aplc%3Apg3zlnog4fdtsy4yu6nh46fi%2Fapp.bsky.feed.post%2F3mpttjje4ic2g",
      "source": "bluesky",
      "published_at": "2026-07-04T19:51:45Z",
      "title": "Coward gobbling rebounds. Boozer’s such a good passer. He’ll assist Edey so much if Edey can stay on the floor.",
      "url": "https://bsky.app/profile/chrisherrington.bsky.social/post/3mpttjje4ic2g",
      "author": "Chris Herrington",
      "thumbnail": null,
      "body_excerpt": "Coward gobbling rebounds. Boozer’s such a good passer. He’ll assist Edey so much if Edey can stay on the floor.",
      "players": [],
      "teams": [],
      "trending_score": 0.3265
    },
    {
      "id": "bs-did%3Aplc%3As42iw2fbfmgsgh7hdtvvoaao%2Fapp.bsky.feed.post%2F3mpttce3h2c26",
      "source": "bluesky",
      "published_at": "2026-07-04T19:47:44Z",
      "title": "Cameron Boozer catch and shoot three",
      "url": "https://bsky.app/profile/hoopinformatics.bsky.social/post/3mpttce3h2c26",
      "author": "Hoop Informatics",
      "thumbnail": "https://video.bsky.app/watch/did%3Aplc%3As42iw2fbfmgsgh7hdtvvoaao/bafkreidkp34guawc5b6qpdp5asjxbnzjzstlv4gspeyy427dvk5frzfv6u/thumbnail.jpg",
      "body_excerpt": "Cameron Boozer catch and shoot three",
      "players": [],
      "teams": [],
      "media": {
        "type": "video",
        "thumbnail": "https://video.bsky.app/watch/did%3Aplc%3As42iw2fbfmgsgh7hdtvvoaao/bafkreidkp34guawc5b6qpdp5asjxbnzjzstlv4gspeyy427dvk5frzfv6u/thumbnail.jpg",
        "playlist": "https://video.bsky.app/watch/did%3Aplc%3As42iw2fbfmgsgh7hdtvvoaao/bafkreidkp34guawc5b6qpdp5asjxbnzjzstlv4gspeyy427dvk5frzfv6u/playlist.m3u8"
      },
      "trending_score": 0.3116
    },
    {
      "id": "bs-did%3Aplc%3Arrh5me656wmncolysevqhc4y%2Fapp.bsky.feed.post%2F3mpttaphges2w",
      "source": "bluesky",
      "published_at": "2026-07-04T19:46:49Z",
      "title": "Have watched enough clips of new Sixers for a lifetime over the last 24 hours. The first of many film study stories:",
      "url": "https://bsky.app/profile/adamaaronson.bsky.social/post/3mpttaphges2w",
      "author": "Adam Aaronson",
      "thumbnail": null,
      "body_excerpt": "Have watched enough clips of new Sixers for a lifetime over the last 24 hours. The first of many film study stories:",
      "players": [],
      "teams": [
        "los-angeles-clippers",
        "philadelphia-76ers"
      ],
      "trending_score": 0.3083
    },
    {
      "id": "bs-did%3Aplc%3As42iw2fbfmgsgh7hdtvvoaao%2Fapp.bsky.feed.post%2F3mptt2squy226",
      "source": "bluesky",
      "published_at": "2026-07-04T19:43:31Z",
      "title": "Aday Mara finds the cutting Brooks Barnhizer",
      "url": "https://bsky.app/profile/hoopinformatics.bsky.social/post/3mptt2squy226",
      "author": "Hoop Informatics",
      "thumbnail": "https://video.bsky.app/watch/did%3Aplc%3As42iw2fbfmgsgh7hdtvvoaao/bafkreifnuqpxptct625yo7r6l33h2ruui2m7hzwhbkmzhw6ps6aq6c4xim/thumbnail.jpg",
      "body_excerpt": "Aday Mara finds the cutting Brooks Barnhizer",
      "players": [
        "brooks-barnhizer"
      ],
      "teams": [],
      "media": {
        "type": "video",
        "thumbnail": "https://video.bsky.app/watch/did%3Aplc%3As42iw2fbfmgsgh7hdtvvoaao/bafkreifnuqpxptct625yo7r6l33h2ruui2m7hzwhbkmzhw6ps6aq6c4xim/thumbnail.jpg",
        "playlist": "https://video.bsky.app/watch/did%3Aplc%3As42iw2fbfmgsgh7hdtvvoaao/bafkreifnuqpxptct625yo7r6l33h2ruui2m7hzwhbkmzhw6ps6aq6c4xim/playlist.m3u8"
      },
      "trending_score": 0.2971
    },
    {
      "id": "bs-did%3Aplc%3Aluofuy2uw7g4vsd2vbwidtel%2Fapp.bsky.feed.post%2F3mptsvy2cz22o",
      "source": "bluesky",
      "published_at": "2026-07-04T19:40:49Z",
      "title": "Americas World Cup Qualifiers standouts from yesterday:",
      "url": "https://bsky.app/profile/keithsmithnba.bsky.social/post/3mptsvy2cz22o",
      "author": "KeithSmithNBA",
      "thumbnail": null,
      "body_excerpt": "Americas World Cup Qualifiers standouts from yesterday:\n\n🏀Jay Huff: 12 pts, 4 blks\n🏀Mike James: 15 pts, 13 asts\n🏀Terry Taylor: 14 pts, 6 rebs\n🏀VJ Edgecombe: 26/8/3, 4 steals\n🏀Kai Jones: 12 pts, 3 blks\n🏀Shai Gilgeous-Alexander: 26 pts, 2 stls, 2 blks\n🏀Andrew Nembhard: 23/5/4",
      "players": [],
      "teams": [],
      "trending_score": 0.2884
    },
    {
      "id": "bs-did%3Aplc%3Aszxkt3ekyjatlwd7jknsmtv4%2Fapp.bsky.feed.post%2F3mptsvmmrqk2h",
      "source": "bluesky",
      "published_at": "2026-07-04T19:40:37Z",
      "title": "Thank you to our founding fathers",
      "url": "https://bsky.app/profile/erikg503.bsky.social/post/3mptsvmmrqk2h",
      "author": "Erik García Gundersen",
      "thumbnail": "https://cdn.bsky.app/img/feed_fullsize/plain/did:plc:szxkt3ekyjatlwd7jknsmtv4/bafkreih5ruwjdyk6ps4rufoqienpguv5ka6r7j4ltgjs2qn77ic37nuzae",
      "body_excerpt": "Thank you to our founding fathers",
      "players": [],
      "teams": [],
      "media": {
        "type": "image",
        "images": [
          {
            "url": "https://cdn.bsky.app/img/feed_fullsize/plain/did:plc:szxkt3ekyjatlwd7jknsmtv4/bafkreih5ruwjdyk6ps4rufoqienpguv5ka6r7j4ltgjs2qn77ic37nuzae",
            "alt": "Jeff Goldblum and Will Smith in Independence Day "
          }
        ]
      },
      "trending_score": 0.2877
    },
    {
      "id": "bs-did%3Aplc%3Ayvy5ax23zpmoearxn6xsgqzf%2Fapp.bsky.feed.post%2F3mptsugljls2s",
      "source": "bluesky",
      "published_at": "2026-07-04T19:39:57Z",
      "title": "cam boozer",
      "url": "https://bsky.app/profile/btrowland.bsky.social/post/3mptsugljls2s",
      "author": "Brad Rowland",
      "thumbnail": null,
      "body_excerpt": "cam boozer\n\ngood at basketball",
      "players": [],
      "teams": [],
      "trending_score": 0.2856
    },
    {
      "id": "gn-cde85e7064d0aa9d",
      "source": "google-news",
      "published_at": "2026-07-04T19:29:00Z",
      "title": "Los Angeles Lakers Sign Peter Suder to Two-Way Contract",
      "url": "https://news.google.com/rss/articles/CBMigAFBVV95cUxQVENVU0ttR3FSMFZPOWN5QlU3dy1CVTF0RjVvcGhmNnNfeWpadGRIOXRPNEYzR2pPa0gxMEVRaTRGT3BHQlhlWEZJQkV0a2s5OWFocEI0cy1rcVlZLU9YQWptRng2NHJrRjJxZ3V5RnY0UjRpSkk5WDJGZjRvOEQ4bA?oc=5",
      "author": "NBA.com",
      "thumbnail": null,
      "body_excerpt": "Los Angeles Lakers Sign Peter Suder to Two-Way Contract NBA.com",
      "players": [],
      "teams": [
        "los-angeles-lakers"
      ],
      "trending_score": 0.2803
    },
    {
      "id": "bs-did%3Aplc%3As42iw2fbfmgsgh7hdtvvoaao%2Fapp.bsky.feed.post%2F3mptsq3jwus26",
      "source": "bluesky",
      "published_at": "2026-07-04T19:37:31Z",
      "title": "(no text)",
      "url": "https://bsky.app/profile/hoopinformatics.bsky.social/post/3mptsq3jwus26",
      "author": "Hoop Informatics",
      "thumbnail": "https://cdn.bsky.app/img/feed_fullsize/plain/did:plc:s42iw2fbfmgsgh7hdtvvoaao/bafkreibcwa4at5ibtxsycdap353ux5a6kg5yj52w6d5dmagexb7pw3muqy",
      "body_excerpt": "",
      "players": [],
      "teams": [],
      "media": {
        "type": "image",
        "images": [
          {
            "url": "https://cdn.bsky.app/img/feed_fullsize/plain/did:plc:s42iw2fbfmgsgh7hdtvvoaao/bafkreibcwa4at5ibtxsycdap353ux5a6kg5yj52w6d5dmagexb7pw3muqy",
            "alt": "Salt Lake City Summer League starting lineups graphic for Memphis vs. Oklahoma City. Memphis Grizzlies (left): Javon Small (10) guard, Cedric Coward (23) guard, Olivier-Maxence Prosper (18) forward, Cameron Boozer (27) forward, Taylor Hendricks (22) center. Oklahoma City Thunder (right): Bennett Stirtz (14) guard, Josh Dix (21) guard, Brooks Barnhizer (23) forward, Otega Oweh (13) forward, Aday Mara (15) center. Team logos flank each roster."
          }
        ]
      },
      "trending_score": 0.2783
    },
    {
      "id": "gn-7cbbbef54ae9740e",
      "source": "google-news",
      "published_at": "2026-07-04T19:27:36Z",
      "title": "Grizzlies' Karim Lopez, Walter Clayton Jr. to miss SLC Summer League games",
      "url": "https://news.google.com/rss/articles/CBMijgFBVV95cUxPekF5T084RHVwOS01bExNMXp0MXNPSnJ3V0F2Rkl3WXJfYmlYWlZrMlJyQXZrZjd6elZwQjlwUTV2eExOYlNwZFQzcjJLOW5haG84WWs4b1dNRkpQbGRYUEZnS25yTWhjQVNSeDhHNFNuTDJuQVRpTVo4TDFERXNhMWU4dkhtanEzQWNDM09B?oc=5",
      "author": "Yahoo Sports",
      "thumbnail": null,
      "body_excerpt": "Grizzlies' Karim Lopez, Walter Clayton Jr. to miss SLC Summer League games Yahoo Sports",
      "players": [
        "walter-clayton-jr"
      ],
      "teams": [
        "memphis-grizzlies"
      ],
      "trending_score": 0.2764
    },
    {
      "id": "gn-4eccdbcfd82129a8",
      "source": "google-news",
      "published_at": "2026-07-04T19:26:00Z",
      "title": "Los Angeles Lakers Re-Sign Guard Chris Mañon",
      "url": "https://news.google.com/rss/articles/CBMickFVX3lxTE90U3BvWENPNUhfWXNVZkRHSURuWXBWby1DZHctYUFrSXZYRU9CZGpLZEF6RTZ6bmRsUUtIZXFORWNieml5ZTVBVzk4N3d6UnNFR0xudFFfa0FZS0pzZWVrVTBvMEttVlBQNmNmSGROejRPUQ?oc=5",
      "author": "NBA.com",
      "thumbnail": null,
      "body_excerpt": "Los Angeles Lakers Re-Sign Guard Chris Mañon NBA.com",
      "players": [
        "chris-manon"
      ],
      "teams": [
        "los-angeles-lakers"
      ],
      "trending_score": 0.272
    },
    {
      "id": "bs-did%3Aplc%3Awzpgt6z5dcqldirvcapkpm6w%2Fapp.bsky.feed.post%2F3mptsbavud22s",
      "source": "bluesky",
      "published_at": "2026-07-04T19:29:13Z",
      "title": "What a game. ",
      "url": "https://bsky.app/profile/zenakeita.bsky.social/post/3mptsbavud22s",
      "author": "Zena Keita",
      "thumbnail": null,
      "body_excerpt": "What a game. \n\nAlso shout out Kaila Charles. She was CLUTCH on the boards and hitting that 3. Whew.\n\nAtlanta needs Bri Jones back now.",
      "players": [],
      "teams": [],
      "trending_score": 0.2554
    },
    {
      "id": "bs-did%3Aplc%3Apaf4vetn26bu7uggsie3vyrc%2Fapp.bsky.feed.post%2F3mpts5xepxk2w",
      "source": "bluesky",
      "published_at": "2026-07-04T19:27:23Z",
      "title": "That gruesome leg injury was a setback but Taylor Hendricks still looks like a worthy prospect",
      "url": "https://bsky.app/profile/lawmurraythenu.bsky.social/post/3mpts5xepxk2w",
      "author": "Law Murray 📘",
      "thumbnail": null,
      "body_excerpt": "That gruesome leg injury was a setback but Taylor Hendricks still looks like a worthy prospect",
      "players": [
        "taylor-hendricks"
      ],
      "teams": [],
      "trending_score": 0.2507
    },
    {
      "id": "gn-d64a7a914241a4b1",
      "source": "google-news",
      "published_at": "2026-07-04T19:16:59Z",
      "title": "Nembhard, Zubac, Huff and Thompson Shine in International Play",
      "url": "https://news.google.com/rss/articles/CBMirAFBVV95cUxOa0NvZVI2Z3NxS2dYdkN0UEJQb2RIaS1mTlNZY2RsM2FXcEltSU5zcTdQR0VWWEFRdl9Sbjd2V2VrQUVlZDd5NE0tdDdwMGU0bThsdVlxcXU2dlN4M3BvNnVpT2ZiZzBuUGZwZ21QcG8xckZSUXFtUmwzakhNX2ZWMUp6ejFZamM5cTdodmFaY0MxOXZnNFNJbjFVdHIzVFdORm1oMkF4YzFULWpu?oc=5",
      "author": "Sports Illustrated",
      "thumbnail": null,
      "body_excerpt": "Nembhard, Zubac, Huff and Thompson Shine in International Play Sports Illustrated",
      "players": [
        "ivica-zubac"
      ],
      "teams": [],
      "trending_score": 0.2496
    },
    {
      "id": "bs-did%3Aplc%3Awzpgt6z5dcqldirvcapkpm6w%2Fapp.bsky.feed.post%2F3mptrz3qzes2s",
      "source": "bluesky",
      "published_at": "2026-07-04T19:24:40Z",
      "title": "THIS GAME HAS ME SCREAMING",
      "url": "https://bsky.app/profile/zenakeita.bsky.social/post/3mptrz3qzes2s",
      "author": "Zena Keita",
      "thumbnail": null,
      "body_excerpt": "THIS GAME HAS ME SCREAMING",
      "players": [],
      "teams": [],
      "trending_score": 0.2441
    },
    {
      "id": "gn-f8952821893e2393",
      "source": "google-news",
      "published_at": "2026-07-04T19:14:31Z",
      "title": "Milwaukee Bucks vs Golden State Warriors Blue Jul 4, 2026 Box Scores",
      "url": "https://news.google.com/rss/articles/CBMiZ0FVX3lxTFA2MXNHWnNQUXc0N0lXcGdCRzdnaV93bFBoNWZGaWU5WXhtclg5dFUtMktqOG85NWNRaWdPNlBOanItNFlZLWx3andpaHdPUjFSakoyUGRaNFlaZlNJeXJ1UThqWkpVZDg?oc=5",
      "author": "NBA.com",
      "thumbnail": null,
      "body_excerpt": "Milwaukee Bucks vs Golden State Warriors Blue Jul 4, 2026 Box Scores NBA.com",
      "players": [],
      "teams": [
        "golden-state-warriors",
        "milwaukee-bucks"
      ],
      "trending_score": 0.2439
    },
    {
      "id": "bs-did%3Aplc%3Akxythy36vqgzttgcpbckbmxi%2Fapp.bsky.feed.post%2F3mptrydhtb22f",
      "source": "bluesky",
      "published_at": "2026-07-04T19:24:14Z",
      "title": "Happy MJ to those: www.youtube.com/watch?v=hajl...",
      "url": "https://bsky.app/profile/sheacarlson.bsky.social/post/3mptrydhtb22f",
      "author": "Shea",
      "thumbnail": "https://cdn.bsky.app/img/feed_thumbnail/plain/did:plc:kxythy36vqgzttgcpbckbmxi/bafkreihb6odfeqlks4pa52pqulf3l6rcor45j6uhjieif4kssjfrx6t5du",
      "body_excerpt": "Happy MJ to those: www.youtube.com/watch?v=hajl...",
      "players": [],
      "teams": [],
      "media": {
        "type": "link",
        "uri": "https://www.youtube.com/watch?v=hajltNGPfps",
        "title": "MJ Lenderman - Manning Fireworks (Full Album Stream)",
        "description": "YouTube video by MJ Lenderman",
        "thumb": "https://cdn.bsky.app/img/feed_thumbnail/plain/did:plc:kxythy36vqgzttgcpbckbmxi/bafkreihb6odfeqlks4pa52pqulf3l6rcor45j6uhjieif4kssjfrx6t5du"
      },
      "trending_score": 0.2431
    },
    {
      "id": "bs-did%3Aplc%3Awzpgt6z5dcqldirvcapkpm6w%2Fapp.bsky.feed.post%2F3mptry4dhnc2s",
      "source": "bluesky",
      "published_at": "2026-07-04T19:24:07Z",
      "title": "ATLANTA’S DEFENSE!!",
      "url": "https://bsky.app/profile/zenakeita.bsky.social/post/3mptry4dhnc2s",
      "author": "Zena Keita",
      "thumbnail": null,
      "body_excerpt": "ATLANTA’S DEFENSE!!",
      "players": [],
      "teams": [],
      "trending_score": 0.2428
    },
    {
      "id": "bs-did%3Aplc%3Awzpgt6z5dcqldirvcapkpm6w%2Fapp.bsky.feed.post%2F3mptruiti5s2s",
      "source": "bluesky",
      "published_at": "2026-07-04T19:22:06Z",
      "title": "GABBY WILLIAMS IS A STAR.",
      "url": "https://bsky.app/profile/zenakeita.bsky.social/post/3mptruiti5s2s",
      "author": "Zena Keita",
      "thumbnail": null,
      "body_excerpt": "GABBY WILLIAMS IS A STAR.",
      "players": [],
      "teams": [],
      "trending_score": 0.2381
    },
    {
      "id": "bs-did%3Aplc%3Awlwlvnq25nzwvz43crqo7apu%2Fapp.bsky.feed.post%2F3mptrucl42c2b",
      "source": "bluesky",
      "published_at": "2026-07-04T19:21:59Z",
      "title": "messing around with a chart for our next newsletter: the top 16 teams in the WC broken down by the countries of the clubs their players play in!",
      "url": "https://bsky.app/profile/shrikhalpada.dev/post/3mptrucl42c2b",
      "author": "shri",
      "thumbnail": "https://cdn.bsky.app/img/feed_fullsize/plain/did:plc:wlwlvnq25nzwvz43crqo7apu/bafkreievxb4aonhbvimpqrs5nixlddlbtyghcbvlar6pjbvkoyezgyfn6i",
      "body_excerpt": "messing around with a chart for our next newsletter: the top 16 teams in the WC broken down by the countries of the clubs their players play in!\n\nColombia and Morocco have the most \"diverse\" teams by this metric with 13 and 12 clubs respectively\n\nEngland and Spain, unsurprisingly, only have 4",
      "players": [],
      "teams": [],
      "media": {
        "type": "image",
        "images": [
          {
            "url": "https://cdn.bsky.app/img/feed_fullsize/plain/did:plc:wlwlvnq25nzwvz43crqo7apu/bafkreievxb4aonhbvimpqrs5nixlddlbtyghcbvlar6pjbvkoyezgyfn6i",
            "alt": "Sankey diagram showing where players from the 16 remaining World Cup national teams play club soccer, linking each national team to the country of their clubs; England is the largest destination, followed by Spain, France, Italy, and Germany."
          }
        ]
      },
      "trending_score": 0.2378
    },
    {
      "id": "bs-did%3Aplc%3A4xpj3xjxsxxcuh3ghaulzdqu%2Fapp.bsky.feed.post%2F3mptrrgxhkc27",
      "source": "bluesky",
      "published_at": "2026-07-04T19:20:23Z",
      "title": "From his most recent, \"Untrue Stories of Fiction,\" available through his website: deepthoughtsbyjackhandey.com/untrue-stori...",
      "url": "https://bsky.app/profile/yourmandevine.bsky.social/post/3mptrrgxhkc27",
      "author": "Dan Devine",
      "thumbnail": "https://cdn.bsky.app/img/feed_thumbnail/plain/did:plc:4xpj3xjxsxxcuh3ghaulzdqu/bafkreibj6c26ihmbh7tjs3gyx4xgliqj7xorhx5pd5noaxqkejpks6qjci",
      "body_excerpt": "From his most recent, \"Untrue Stories of Fiction,\" available through his website: deepthoughtsbyjackhandey.com/untrue-stori...",
      "players": [],
      "teams": [],
      "media": {
        "type": "link",
        "uri": "https://deepthoughtsbyjackhandey.com/untrue-stories-bookstore/",
        "title": "Untrue Stories of Fiction - Deep Thoughts by Jack Handey",
        "description": "$19.95PaperbackLimited first edition, signed by authorFree personalized inscriptionSorry, no refunds (not that you’d want one)Shipping (USA)$5.99 per orderPlease allow 1-2 weeks for delivery(Sorry, no...",
        "thumb": "https://cdn.bsky.app/img/feed_thumbnail/plain/did:plc:4xpj3xjxsxxcuh3ghaulzdqu/bafkreibj6c26ihmbh7tjs3gyx4xgliqj7xorhx5pd5noaxqkejpks6qjci"
      },
      "trending_score": 0.2342
    },
    {
      "id": "gn-46bd14a25a39b465",
      "source": "google-news",
      "published_at": "2026-07-04T19:07:30Z",
      "title": "Bucks vs. Warriors Blue (Jul 4, 2026) Box Score",
      "url": "https://news.google.com/rss/articles/CBMimwFBVV95cUxOcHpXUWxjeDBvNjVxYnFTUUs0M2xSb0V0dWJ5RFV1alJaRWJvS0JWQWJVRi1hU1JmX3M5OVdRTXN2TkdEZnVnLV9wMmY2aFF5VGVWZlZ4RHZZVmRZUGJCdlpGTjJuVUk0ekpXWnd0YXlmVFQ1anJteUhzeUlPT1Vha2RiVXRaT2FTNXZVT3ROR0d5N0prZlluVHRPNA?oc=5",
      "author": "ESPN",
      "thumbnail": null,
      "body_excerpt": "Bucks vs. Warriors Blue (Jul 4, 2026) Box Score ESPN",
      "players": [],
      "teams": [
        "golden-state-warriors",
        "milwaukee-bucks"
      ],
      "trending_score": 0.2291
    },
    {
      "id": "bs-did%3Aplc%3Aluofuy2uw7g4vsd2vbwidtel%2Fapp.bsky.feed.post%2F3mptrjfn6i22o",
      "source": "bluesky",
      "published_at": "2026-07-04T19:15:53Z",
      "title": "The Summer Grizzlies have a lot of legit roster guys. Heck, the lineup they started today is better than some of the lineups they started last regular season!",
      "url": "https://bsky.app/profile/keithsmithnba.bsky.social/post/3mptrjfn6i22o",
      "author": "KeithSmithNBA",
      "thumbnail": null,
      "body_excerpt": "The Summer Grizzlies have a lot of legit roster guys. Heck, the lineup they started today is better than some of the lineups they started last regular season!",
      "players": [],
      "teams": [
        "memphis-grizzlies"
      ],
      "trending_score": 0.2246
    },
    {
      "id": "bs-did%3Aplc%3Amx62ni2prhriaagd7jfa65zk%2Fapp.bsky.feed.post%2F3mptrinauqs2g",
      "source": "bluesky",
      "published_at": "2026-07-04T19:15:28Z",
      "title": "Good screen, roll and finish from Angel Reese.",
      "url": "https://bsky.app/profile/stevejones20.bsky.social/post/3mptrinauqs2g",
      "author": "Steve Jones",
      "thumbnail": "https://video.bsky.app/watch/did%3Aplc%3Amx62ni2prhriaagd7jfa65zk/bafkreidye7bhydgp3uik534hnlxqmqnq23nyaw55lidnqsp5km47vtjf6e/thumbnail.jpg",
      "body_excerpt": "Good screen, roll and finish from Angel Reese.",
      "players": [],
      "teams": [],
      "media": {
        "type": "video",
        "thumbnail": "https://video.bsky.app/watch/did%3Aplc%3Amx62ni2prhriaagd7jfa65zk/bafkreidye7bhydgp3uik534hnlxqmqnq23nyaw55lidnqsp5km47vtjf6e/thumbnail.jpg",
        "playlist": "https://video.bsky.app/watch/did%3Aplc%3Amx62ni2prhriaagd7jfa65zk/bafkreidye7bhydgp3uik534hnlxqmqnq23nyaw55lidnqsp5km47vtjf6e/playlist.m3u8"
      },
      "trending_score": 0.2237
    },
    {
      "id": "gn-446d801fbcbbd8aa",
      "source": "google-news",
      "published_at": "2026-07-04T19:04:44Z",
      "title": "Grizzlies vs. Thunder (Jul 4, 2026) Live Score",
      "url": "https://news.google.com/rss/articles/CBMijgFBVV95cUxNelMyZVdJYUlWWVZ2NnZzc1ROay1TSElSSUJldHFyRUVvQ1oycXhESExWZG4zLWdJNjJoNXFfb3dKdDZETzd0c0k1TjlRUUZxcVpVZVlYRTdwM0gtMGx6aGRtNk1Ra2NieUVjT3VDT0FfSncyMFA2c3RfZmJNX1I4eWphV0NuOGRsQlVEVVlB?oc=5",
      "author": "ESPN",
      "thumbnail": null,
      "body_excerpt": "Grizzlies vs. Thunder (Jul 4, 2026) Live Score ESPN",
      "players": [],
      "teams": [
        "memphis-grizzlies",
        "oklahoma-city-thunder"
      ],
      "trending_score": 0.2236
    },
    {
      "id": "gn-50a678b8f851f545",
      "source": "google-news",
      "published_at": "2026-07-04T19:04:44Z",
      "title": "Grizzlies vs. Thunder (Jul 4, 2026) Box Score",
      "url": "https://news.google.com/rss/articles/CBMikwFBVV95cUxOVUU4UzFtdUZrWk1NdGtldlBraGwtcGJ3bTdYZ3ZmVlV3LWdpaTJFSUFld0U1UEVYeS0yZXl6bE5tcUp0bjM1MFNjS25KUzNzQ04teUlxLXhNWXZlWWZvMngwMXkwYU02alFzQ1lKeHNuaVFiSnBaUFA1T2NBZ3QzLWpxOWdPb1pqNUxYU2tpbzhKMmM?oc=5",
      "author": "ESPN",
      "thumbnail": null,
      "body_excerpt": "Grizzlies vs. Thunder (Jul 4, 2026) Box Score ESPN",
      "players": [],
      "teams": [
        "memphis-grizzlies",
        "oklahoma-city-thunder"
      ],
      "trending_score": 0.2236
    },
    {
      "id": "gn-50d77e50b97a07de",
      "source": "google-news",
      "published_at": "2026-07-04T19:04:35Z",
      "title": "Bucks vs. Warriors Blue (Jul 4, 2026) Live Score",
      "url": "https://news.google.com/rss/articles/CBMilgFBVV95cUxNQWxIZW5lU0I0SlowLXpYZmtndlhtSmdublNxdGhqUlFaUlJnYzVRdnB5ZDZiZ09COTFiV0N6VElEQ2RkRjhOOUQtcmo5em1XVWM5ckR6TjVOVUY4NXQ3eXpFaW5mWmZTZWg0b0FfQWY4ZTNkQ0NvLWh3UjJleW9TNWFZeHFaQlRTbUpPcXo0Y2w3dE5iSUE?oc=5",
      "author": "ESPN",
      "thumbnail": null,
      "body_excerpt": "Bucks vs. Warriors Blue (Jul 4, 2026) Live Score ESPN",
      "players": [],
      "teams": [
        "golden-state-warriors",
        "milwaukee-bucks"
      ],
      "trending_score": 0.2233
    },
    {
      "id": "gn-af2f7856d6bdcc74",
      "source": "google-news",
      "published_at": "2026-07-04T19:03:22Z",
      "title": "Grizzlies' Walter Clayton: Won't play in Salt Lake City",
      "url": "https://news.google.com/rss/articles/CBMipgFBVV95cUxPYW1NZktSLWNaZDJ6SkM0aWhpZlI1U1NQaXFhb2Nlai1kNEtxaWlhUWVXR2UtczgxNkI2NXJJelZMZi1jcl9JSDk3TWwwUHJPNXhYRlNya0ZQd2pRcGRzaU5JME93dE1rYnNEdE93RFoxWlhkakxSbEZRSWJtdUVWa0pHVk5pUXhaMmktTF9RdHF3RF9JeFpmWk8yYjB5XzRsZHJTSTVR?oc=5",
      "author": "CBS Sports",
      "thumbnail": null,
      "body_excerpt": "Grizzlies' Walter Clayton: Won't play in Salt Lake City CBS Sports",
      "players": [],
      "teams": [
        "memphis-grizzlies"
      ],
      "trending_score": 0.221
    },
    {
      "id": "gn-c4ff7814e0816db6",
      "source": "google-news",
      "published_at": "2026-07-04T19:01:00Z",
      "title": "Tim Hardaway Sr. has simple reason for refusing to let son use retired Heat number",
      "url": "https://news.google.com/rss/articles/CBMirwFBVV95cUxNUTlxNldWekdRcDAtTXVJN0I0RE9VZFZaaWlqb29LMmhzUGpMMlNDdWFBVlJjZ2pRSmdYbUtLdDNIdWhLTmM5VHNubG9IWUpHZHpuQkhiOU03T3ZNYWNQM0xyUk0yd3dNNTFXODZGeWpRajd6UWVUZGdXOVNZeGdWRV95TmJrVnBtTTd4Uy1XSWJzbjNwSWZjSUlxdWtDaFF4cnAzNVo3Q2ppOGNsQkZj?oc=5",
      "author": "New York Post",
      "thumbnail": null,
      "body_excerpt": "Tim Hardaway Sr. has simple reason for refusing to let son use retired Heat number New York Post",
      "players": [],
      "teams": [
        "miami-heat"
      ],
      "trending_score": 0.2166
    },
    {
      "id": "bs-did%3Aplc%3Amx62ni2prhriaagd7jfa65zk%2Fapp.bsky.feed.post%2F3mptrblal5s2g",
      "source": "bluesky",
      "published_at": "2026-07-04T19:11:31Z",
      "title": "Not much hesitation from Cam Boozer on this three. Grizzlies have moved him around the board early, versatility stands out.",
      "url": "https://bsky.app/profile/stevejones20.bsky.social/post/3mptrblal5s2g",
      "author": "Steve Jones",
      "thumbnail": "https://video.bsky.app/watch/did%3Aplc%3Amx62ni2prhriaagd7jfa65zk/bafkreiav4kmx24bqlsn2ex65iog4ybloxarume7lvfqkk4mvervonoq32q/thumbnail.jpg",
      "body_excerpt": "Not much hesitation from Cam Boozer on this three. Grizzlies have moved him around the board early, versatility stands out.",
      "players": [],
      "teams": [
        "memphis-grizzlies"
      ],
      "media": {
        "type": "video",
        "thumbnail": "https://video.bsky.app/watch/did%3Aplc%3Amx62ni2prhriaagd7jfa65zk/bafkreiav4kmx24bqlsn2ex65iog4ybloxarume7lvfqkk4mvervonoq32q/thumbnail.jpg",
        "playlist": "https://video.bsky.app/watch/did%3Aplc%3Amx62ni2prhriaagd7jfa65zk/bafkreiav4kmx24bqlsn2ex65iog4ybloxarume7lvfqkk4mvervonoq32q/playlist.m3u8"
      },
      "trending_score": 0.2158
    },
    {
      "id": "gn-bbfa8c6561783bca",
      "source": "google-news",
      "published_at": "2026-07-04T18:58:47Z",
      "title": "Grizzlies Open Salt Lake City Summer League Slate With Three Things to Watch",
      "url": "https://news.google.com/rss/articles/CBMihAFBVV95cUxNY215Ry1uMzZRN3F6N0xuLTdwRTE2eFVuM05pVDZ6dWlOYUZLM2lZd2h5TW1zNW92eVlzSGhlZHR4aFJsTi1ycUFIQzNCYURvN0l5OEdFR2stR09xbXFndTY1bUQ5R2k5UDhCM21hdWl2dmluSzBUWXNXVXNBX1JBSGltSWk?oc=5",
      "author": "Yahoo Sports",
      "thumbnail": null,
      "body_excerpt": "Grizzlies Open Salt Lake City Summer League Slate With Three Things to Watch Yahoo Sports",
      "players": [],
      "teams": [
        "memphis-grizzlies"
      ],
      "trending_score": 0.2126
    },
    {
      "id": "gn-6a69c4d133d13002",
      "source": "google-news",
      "published_at": "2026-07-04T18:58:32Z",
      "title": "Dalton Knecht & Another Lakers Star on Trade Alert Amid Viral Practice Video, Per Reports",
      "url": "https://news.google.com/rss/articles/CBMiigFBVV95cUxPTk15cnhBWjNIejNiZEU2ZmctYzROVUhLREZYWlV2eVdKd0VqY1BpbDVNbXVMZDM1a3hzY0NaQUxoanIyWGRtLU5BODF6TXFSY3hOY1hDbExHS09NTnBVb2tRQ08wN0M2bXBOX0hTRDRpTHVxbVd6Sm96S2tfOFFJZTBrLUpyQ1hPSlE?oc=5",
      "author": "Yahoo Sports",
      "thumbnail": null,
      "body_excerpt": "Dalton Knecht & Another Lakers Star on Trade Alert Amid Viral Practice Video, Per Reports Yahoo Sports",
      "players": [
        "dalton-knecht"
      ],
      "teams": [
        "los-angeles-lakers"
      ],
      "trending_score": 0.2121
    },
    {
      "id": "bs-did%3Aplc%3Apaf4vetn26bu7uggsie3vyrc%2Fapp.bsky.feed.post%2F3mptqzfduk22w",
      "source": "bluesky",
      "published_at": "2026-07-04T19:06:56Z",
      "title": "Grizzlies have the BC memorial patch. damn",
      "url": "https://bsky.app/profile/lawmurraythenu.bsky.social/post/3mptqzfduk22w",
      "author": "Law Murray 📘",
      "thumbnail": null,
      "body_excerpt": "Grizzlies have the BC memorial patch. damn",
      "players": [],
      "teams": [
        "memphis-grizzlies"
      ],
      "trending_score": 0.2072
    },
    {
      "id": "bs-did%3Aplc%3Amx62ni2prhriaagd7jfa65zk%2Fapp.bsky.feed.post%2F3mptqxzbbuk2g",
      "source": "bluesky",
      "published_at": "2026-07-04T19:06:10Z",
      "title": "Well that's quite the start for Cam Boozer.",
      "url": "https://bsky.app/profile/stevejones20.bsky.social/post/3mptqxzbbuk2g",
      "author": "Steve Jones",
      "thumbnail": "https://video.bsky.app/watch/did%3Aplc%3Amx62ni2prhriaagd7jfa65zk/bafkreig4pemokk44hv3aa54fl5liwiifefsp7mn44utmiwscvb6vlaobz4/thumbnail.jpg",
      "body_excerpt": "Well that's quite the start for Cam Boozer.",
      "players": [],
      "teams": [],
      "media": {
        "type": "video",
        "thumbnail": "https://video.bsky.app/watch/did%3Aplc%3Amx62ni2prhriaagd7jfa65zk/bafkreig4pemokk44hv3aa54fl5liwiifefsp7mn44utmiwscvb6vlaobz4/thumbnail.jpg",
        "playlist": "https://video.bsky.app/watch/did%3Aplc%3Amx62ni2prhriaagd7jfa65zk/bafkreig4pemokk44hv3aa54fl5liwiifefsp7mn44utmiwscvb6vlaobz4/playlist.m3u8"
      },
      "trending_score": 0.2058
    },
    {
      "id": "bs-did%3Aplc%3A75z3gabuwl6uvv7pootuuvgn%2Fapp.bsky.feed.post%2F3mptqu6m23e2h",
      "source": "bluesky",
      "published_at": "2026-07-04T19:04:01Z",
      "title": "#Lakers reportedly like how Sandro Mamukelashvili fits alongside Walker Kessler.",
      "url": "https://bsky.app/profile/lakersnation.bsky.social/post/3mptqu6m23e2h",
      "author": "LakersNation.com",
      "thumbnail": "https://cdn.bsky.app/img/feed_thumbnail/plain/did:plc:75z3gabuwl6uvv7pootuuvgn/bafkreicbbkahku7hlle26hozyawqfqlwzqiehxqipmc22cuj6hgsghitby",
      "body_excerpt": "#Lakers reportedly like how Sandro Mamukelashvili fits alongside Walker Kessler.\nlakersnation.com/lakers-repor...",
      "players": [
        "sandro-mamukelashvili",
        "walker-kessler"
      ],
      "teams": [
        "los-angeles-lakers"
      ],
      "media": {
        "type": "link",
        "uri": "https://lakersnation.com/lakers-reportedly-like-sandro-mamukelashvili-fit-with-walker-kessler/",
        "title": "Lakers Reportedly Like Sandro Mamukelashvili's Fit With Walker Kessler",
        "description": "The Los Angeles Lakers reportedly believe Sandro Mamukelashvili would fit nicely alongside new center Walker Kessler.",
        "thumb": "https://cdn.bsky.app/img/feed_thumbnail/plain/did:plc:75z3gabuwl6uvv7pootuuvgn/bafkreicbbkahku7hlle26hozyawqfqlwzqiehxqipmc22cuj6hgsghitby"
      },
      "trending_score": 0.202
    },
    {
      "id": "bs-did%3Aplc%3Apaf4vetn26bu7uggsie3vyrc%2Fapp.bsky.feed.post%2F3mptqsgncqc2w",
      "source": "bluesky",
      "published_at": "2026-07-04T19:03:02Z",
      "title": "Boozer vs Mara 🍿",
      "url": "https://bsky.app/profile/lawmurraythenu.bsky.social/post/3mptqsgncqc2w",
      "author": "Law Murray 📘",
      "thumbnail": null,
      "body_excerpt": "Boozer vs Mara 🍿",
      "players": [],
      "teams": [],
      "trending_score": 0.2003
    },
    {
      "id": "bs-did%3Aplc%3Amx62ni2prhriaagd7jfa65zk%2Fapp.bsky.feed.post%2F3mptqs2rjg22g",
      "source": "bluesky",
      "published_at": "2026-07-04T19:02:50Z",
      "title": "On the latest Dunker Spot with @nekiasnba.bsky.social we talk through the WNBA All-Star starters, reserves and Nekias has rant(s)",
      "url": "https://bsky.app/profile/stevejones20.bsky.social/post/3mptqs2rjg22g",
      "author": "Steve Jones",
      "thumbnail": "https://cdn.bsky.app/img/feed_thumbnail/plain/did:plc:mx62ni2prhriaagd7jfa65zk/bafkreidnuzbitjnzzqrt3f5mkuhwga32lbgysqknp3w452j4rzjffx62ba",
      "body_excerpt": "On the latest Dunker Spot with @nekiasnba.bsky.social we talk through the WNBA All-Star starters, reserves and Nekias has rant(s)\n\nYT: youtu.be/Zgc62pznuao",
      "players": [],
      "teams": [],
      "media": {
        "type": "link",
        "uri": "https://youtu.be/Zgc62pznuao",
        "title": "Caitlin Clark Speaks + WNBA All-Star Roster Reveal!",
        "description": "YouTube video by Yahoo! Sports",
        "thumb": "https://cdn.bsky.app/img/feed_thumbnail/plain/did:plc:mx62ni2prhriaagd7jfa65zk/bafkreidnuzbitjnzzqrt3f5mkuhwga32lbgysqknp3w452j4rzjffx62ba"
      },
      "trending_score": 0.2
    }
  ]
}
