{
  "slug": "moses-moody",
  "name": "Moses Moody",
  "generated_at": "2026-07-04T10:28:17Z",
  "count": 2,
  "items": [
    {
      "id": "bs-did%3Aplc%3A5dwbpojkp6wykwcafasvwroi%2Fapp.bsky.feed.post%2F3mprz65sfxk27",
      "source": "bluesky",
      "published_at": "2026-07-04T02:27:26Z",
      "title": "Moses Moody is at Chase Center signing autographs for fans before the Warriors' first game at the California Classic",
      "url": "https://bsky.app/profile/daltonjohnson.bsky.social/post/3mprz65sfxk27",
      "author": "Dalton Johnson",
      "thumbnail": null,
      "body_excerpt": "Moses Moody is at Chase Center signing autographs for fans before the Warriors' first game at the California Classic",
      "players": [
        "moses-moody"
      ],
      "teams": [
        "golden-state-warriors"
      ]
    },
    {
      "id": "gn-15572b4da26ca8e9",
      "source": "google-news",
      "published_at": "2026-07-02T22:32:28Z",
      "title": "Gary Payton II throws a beautiful dime to Moses Moody",
      "url": "https://news.google.com/rss/articles/CBMiV0FVX3lxTE5RaS1ac3BYX1N0SWlSQzZwM3JFRkctaUpNbXdBVFN5dHFIT2ZzS2lybXVjSlhwa3FZdVVMNGVuMW5Xd3hHRFBWRG91U3g3TF9tajgxLTc1QQ?oc=5",
      "author": "espn.in",
      "thumbnail": null,
      "body_excerpt": "Gary Payton II throws a beautiful dime to Moses Moody espn.in",
      "players": [
        "gary-payton-ii",
        "moses-moody"
      ],
      "teams": []
    }
  ]
}
