{
  "slug": "santi-aldama",
  "name": "Santi Aldama",
  "generated_at": "2026-06-28T22:07:32Z",
  "count": 1,
  "items": [
    {
      "id": "bs-did%3Aplc%3Akvf6pnfrtgek6jqlkpqhgacv%2Fapp.bsky.feed.post%2F3mpeqzzdnpc2n",
      "source": "bluesky",
      "published_at": "2026-06-28T19:57:21Z",
      "title": "While we didn't have the Suns trading for Miles Bridges, @geraldbourguet.bsky.social and I came up with a nearly identical trade for Santi Aldama in our mock offseason.",
      "url": "https://bsky.app/profile/yossigozlan.bsky.social/post/3mpeqzzdnpc2n",
      "author": "Yossi Gozlan",
      "thumbnail": "https://cdn.bsky.app/img/feed_fullsize/plain/did:plc:kvf6pnfrtgek6jqlkpqhgacv/bafkreigpwf6wavxohpndsvz3eakx2htz3w7uluoho3enwtjo4adadeem4a",
      "body_excerpt": "While we didn't have the Suns trading for Miles Bridges, @geraldbourguet.bsky.social and I came up with a nearly identical trade for Santi Aldama in our mock offseason.",
      "players": [
        "miles-bridges",
        "santi-aldama"
      ],
      "teams": [
        "phoenix-suns"
      ],
      "media": {
        "type": "image",
        "images": [
          {
            "url": "https://cdn.bsky.app/img/feed_fullsize/plain/did:plc:kvf6pnfrtgek6jqlkpqhgacv/bafkreigpwf6wavxohpndsvz3eakx2htz3w7uluoho3enwtjo4adadeem4a",
            "alt": ""
          }
        ]
      }
    }
  ]
}
